[{"codigoEmpresa":1,"codigoProducto":1,"codigoComentario":1,"NombreComentario":"Helen","ApellidoComentario":"Fuentes","imagenC":"img\/Usuarios\/Persona2.jpg","Tiempo":10,"Principal":"Este articulo me parece bonito me gustaria que pusieran mas articulos en promocion de este tipo","ComentarioS":[]},{"codigoEmpresa":1,"codigoProducto":1,"codigoComentario":2,"NombreComentario":"Jose","ApellidoComentario":"Rosales","imagenC":"img\/Usuarios\/Persona1.jpg","Tiempo":20,"Principal":"Me gusta lo que tienen en esta empresa","ComentarioS":[]},{"codigoEmpresa":1,"codigoProducto":2,"codigoComentario":1,"NombreComentario":"Erick","ApellidoComentario":"Rosales","imagenC":"img\/Usuarios\/nightSky.jpg","Tiempo":1,"Principal":"Que onda","ComentarioS":[]},{"codigoEmpresa":1,"codigoProducto":1,"codigoComentario":3,"NombreComentario":"Ledith","ApellidoComentario":"Fuentes","imagenC":"img\/Usuarios\/Persona2.jpg","Tiempo":1,"Principal":"hola","ComentarioS":[]}]